cloudKafkaLogger.py
Cloud_Kafka_Logger-0.1.7.dist-info/LICENSE
Cloud_Kafka_Logger-0.1.7.dist-info/METADATA
Cloud_Kafka_Logger-0.1.7.dist-info/WHEEL
Cloud_Kafka_Logger-0.1.7.dist-info/top_level.txt
Cloud_Kafka_Logger-0.1.7.dist-info/RECORD
