Metadata-Version: 2.1
Name: Cloud-Kafka-Logger
Version: 0.1.7
Summary: Send Message To Cloud Kafka Topic
Home-page: UNKNOWN
Author: Ganesh
Author-email: ganeshmoorthy.va@gmail.com
License: UNKNOWN
Platform: UNKNOWN
Classifier: Programming Language :: Python :: 3
Classifier: License :: OSI Approved :: MIT License
Classifier: Operating System :: OS Independent
Requires-Dist: confluent-kafka
